geosocialpy/__init__.py
geosocialpy/data_fetcher.py
geosocialpy/data_visualization.py
geosocialpy/geospatial_analyzer.py
geosocialpy/geospatial_extractor.py
tests/__init__.py
GeoSocialPy-0.1.dist-info/METADATA
GeoSocialPy-0.1.dist-info/WHEEL
GeoSocialPy-0.1.dist-info/top_level.txt
GeoSocialPy-0.1.dist-info/RECORD
